{
  "updated": "2026-04-24",
  "tickers": {
    "BOIL": {
      "last_30d_net": 91657000.0,
      "zscore": -0.61,
      "regime": "BALANCED",
      "pressure": -31.0,
      "latest_nav": 13.1,
      "flow_5d": -37765000.0,
      "flow_20d": 69514000.0
    },
    "KOLD": {
      "last_30d_net": -129266000.0,
      "zscore": 0.25,
      "regime": "BALANCED",
      "pressure": 16.0,
      "latest_nav": 26.21,
      "flow_5d": 8811000.0,
      "flow_20d": -81056000.0
    },
    "3NGL": {
      "last_30d_net": 11540000.0,
      "zscore": -0.25,
      "regime": "BALANCED",
      "pressure": 4.0,
      "latest_nav": 1.08,
      "flow_5d": 2076000.0,
      "flow_20d": 14947000.0
    },
    "HNU": {
      "last_30d_net": 58691000.0,
      "zscore": -0.26,
      "regime": "BALANCED",
      "pressure": -19.0,
      "latest_nav": 9.79,
      "flow_5d": -15290000.0,
      "flow_20d": 37194000.0
    },
    "HND": {
      "last_30d_net": -41537000.0,
      "zscore": 0.48,
      "regime": "BALANCED",
      "pressure": 24.0,
      "latest_nav": 5.11,
      "flow_5d": 10777000.0,
      "flow_20d": -23370000.0
    },
    "3NGS": {
      "last_30d_net": -11584000.0,
      "zscore": 0.3,
      "regime": "BALANCED",
      "pressure": -3.0,
      "latest_nav": 16.4,
      "flow_5d": -265000.0,
      "flow_20d": -12064000.0
    }
  },
  "cross_etf": {
    "bull_flow_30d": 161888000.0,
    "bear_flow_30d": -182387000.0,
    "sentiment": "NEUTRAL"
  }
}