{
  "updated": "2026-04-21",
  "tickers": {
    "BOIL": {
      "last_30d_net": 104932000.0,
      "zscore": -0.16,
      "regime": "BALANCED",
      "pressure": 6.0,
      "latest_nav": 13.63,
      "flow_5d": 31456000.0,
      "flow_20d": 157729000.0
    },
    "KOLD": {
      "last_30d_net": -127913000.0,
      "zscore": 0.47,
      "regime": "BALANCED",
      "pressure": 4.0,
      "latest_nav": 25.26,
      "flow_5d": -14433000.0,
      "flow_20d": -117918000.0
    },
    "3NGL": {
      "last_30d_net": 12365000.0,
      "zscore": -0.23,
      "regime": "BALANCED",
      "pressure": 4.0,
      "latest_nav": 1.15,
      "flow_5d": 4953000.0,
      "flow_20d": 16270000.0
    },
    "HNU": {
      "last_30d_net": 35528000.0,
      "zscore": -0.74,
      "regime": "BALANCED",
      "pressure": -10.0,
      "latest_nav": 10.32,
      "flow_5d": 8983000.0,
      "flow_20d": 79948000.0
    },
    "HND": {
      "last_30d_net": -39026000.0,
      "zscore": 0.66,
      "regime": "BALANCED",
      "pressure": 30.0,
      "latest_nav": 4.88,
      "flow_5d": 292000.0,
      "flow_20d": -51381000.0
    },
    "3NGS": {
      "last_30d_net": -13472000.0,
      "zscore": 0.33,
      "regime": "BALANCED",
      "pressure": -2.0,
      "latest_nav": 15.53,
      "flow_5d": -3677000.0,
      "flow_20d": -11440000.0
    }
  },
  "cross_etf": {
    "bull_flow_30d": 152825000.0,
    "bear_flow_30d": -180411000.0,
    "sentiment": "NEUTRAL"
  }
}