{
  "last_updated": "2026-03-30T15:56:22.139290+00:00",
  "market_status": "open",
  "signals": [
    {
      "type": "vcvi_warning",
      "side": "long",
      "message": "VCVI (252d) = 60.2 \u2014 potential gas bottom \u2014 long/leveraged setup",
      "timestamp": "2026-03-30T15:56:18.209890+00:00",
      "ticker": "BOIL"
    },
    {
      "type": "cvi_warning",
      "side": "long",
      "message": "CVI (252d) = 63.9 \u2014 potential gas bottom \u2014 long/leveraged setup",
      "timestamp": "2026-03-30T15:56:18.209890+00:00",
      "ticker": "BOIL"
    },
    {
      "type": "vcvi_warning",
      "side": "long",
      "message": "VCVI (5d) = 67.1 \u2014 potential gas bottom \u2014 long/leveraged setup",
      "timestamp": "2026-03-30T15:56:19.025284+00:00",
      "ticker": "HNU.TO"
    },
    {
      "type": "vcvi_warning",
      "side": "long",
      "message": "VCVI (10d) = 59.6 \u2014 potential gas bottom \u2014 long/leveraged setup",
      "timestamp": "2026-03-30T15:56:19.025284+00:00",
      "ticker": "HNU.TO"
    },
    {
      "type": "vcvi_warning",
      "side": "long",
      "message": "VCVI (126d) = 62.5 \u2014 potential gas bottom \u2014 long/leveraged setup",
      "timestamp": "2026-03-30T15:56:19.025284+00:00",
      "ticker": "HNU.TO"
    },
    {
      "type": "vcvi_critical",
      "side": "long",
      "message": "VCVI (252d) = 76.0 \u2014 potential gas bottom \u2014 long/leveraged setup",
      "timestamp": "2026-03-30T15:56:19.025284+00:00",
      "ticker": "HNU.TO"
    },
    {
      "type": "cvi_warning",
      "side": "long",
      "message": "CVI (5d) = 75.0 \u2014 potential gas bottom \u2014 long/leveraged setup",
      "timestamp": "2026-03-30T15:56:19.025284+00:00",
      "ticker": "HNU.TO"
    },
    {
      "type": "cvi_warning",
      "side": "long",
      "message": "CVI (10d) = 66.7 \u2014 potential gas bottom \u2014 long/leveraged setup",
      "timestamp": "2026-03-30T15:56:19.025284+00:00",
      "ticker": "HNU.TO"
    },
    {
      "type": "cvi_warning",
      "side": "long",
      "message": "CVI (126d) = 69.8 \u2014 potential gas bottom \u2014 long/leveraged setup",
      "timestamp": "2026-03-30T15:56:19.025284+00:00",
      "ticker": "HNU.TO"
    },
    {
      "type": "cvi_critical",
      "side": "long",
      "message": "CVI (252d) = 84.9 \u2014 potential gas bottom \u2014 long/leveraged setup",
      "timestamp": "2026-03-30T15:56:19.025284+00:00",
      "ticker": "HNU.TO"
    },
    {
      "type": "vcvi_critical",
      "side": "long",
      "message": "VCVI (5d) = 93.0 \u2014 potential gas bottom \u2014 long/leveraged setup",
      "timestamp": "2026-03-30T15:56:19.705897+00:00",
      "ticker": "3NGL.L"
    },
    {
      "type": "vcvi_critical",
      "side": "long",
      "message": "VCVI (10d) = 82.7 \u2014 potential gas bottom \u2014 long/leveraged setup",
      "timestamp": "2026-03-30T15:56:19.705897+00:00",
      "ticker": "3NGL.L"
    },
    {
      "type": "vcvi_warning",
      "side": "long",
      "message": "VCVI (21d) = 55.8 \u2014 potential gas bottom \u2014 long/leveraged setup",
      "timestamp": "2026-03-30T15:56:19.705897+00:00",
      "ticker": "3NGL.L"
    },
    {
      "type": "vcvi_warning",
      "side": "long",
      "message": "VCVI (63d) = 67.5 \u2014 potential gas bottom \u2014 long/leveraged setup",
      "timestamp": "2026-03-30T15:56:19.705897+00:00",
      "ticker": "3NGL.L"
    },
    {
      "type": "vcvi_critical",
      "side": "long",
      "message": "VCVI (126d) = 79.6 \u2014 potential gas bottom \u2014 long/leveraged setup",
      "timestamp": "2026-03-30T15:56:19.705897+00:00",
      "ticker": "3NGL.L"
    },
    {
      "type": "vcvi_critical",
      "side": "long",
      "message": "VCVI (252d) = 86.4 \u2014 potential gas bottom \u2014 long/leveraged setup",
      "timestamp": "2026-03-30T15:56:19.705897+00:00",
      "ticker": "3NGL.L"
    },
    {
      "type": "cvi_critical",
      "side": "long",
      "message": "CVI (5d) = 100.0 \u2014 potential gas bottom \u2014 long/leveraged setup",
      "timestamp": "2026-03-30T15:56:19.705897+00:00",
      "ticker": "3NGL.L"
    },
    {
      "type": "cvi_critical",
      "side": "long",
      "message": "CVI (10d) = 88.9 \u2014 potential gas bottom \u2014 long/leveraged setup",
      "timestamp": "2026-03-30T15:56:19.705897+00:00",
      "ticker": "3NGL.L"
    },
    {
      "type": "cvi_warning",
      "side": "long",
      "message": "CVI (21d) = 60.0 \u2014 potential gas bottom \u2014 long/leveraged setup",
      "timestamp": "2026-03-30T15:56:19.705897+00:00",
      "ticker": "3NGL.L"
    },
    {
      "type": "cvi_warning",
      "side": "long",
      "message": "CVI (63d) = 72.6 \u2014 potential gas bottom \u2014 long/leveraged setup",
      "timestamp": "2026-03-30T15:56:19.705897+00:00",
      "ticker": "3NGL.L"
    },
    {
      "type": "cvi_critical",
      "side": "long",
      "message": "CVI (126d) = 85.6 \u2014 potential gas bottom \u2014 long/leveraged setup",
      "timestamp": "2026-03-30T15:56:19.705897+00:00",
      "ticker": "3NGL.L"
    },
    {
      "type": "cvi_critical",
      "side": "long",
      "message": "CVI (252d) = 92.8 \u2014 potential gas bottom \u2014 long/leveraged setup",
      "timestamp": "2026-03-30T15:56:19.705897+00:00",
      "ticker": "3NGL.L"
    }
  ],
  "pair_status": {
    "BOIL_KOLD": "quiet",
    "HNU.TO_HND.TO": "quiet",
    "3NGL.L_3NGS.L": "quiet"
  },
  "etf_summary": {
    "BOIL": {
      "price": 15.94,
      "change_pct": -99.999586,
      "vps": 15.345218,
      "mwca": false,
      "vol_regime_pct": 55.776892,
      "hv_term_structure": 0.509907
    },
    "HNU.TO": {
      "price": 11.84,
      "change_pct": -99.999998,
      "vps": 34.590476,
      "mwca": false,
      "vol_regime_pct": 60.557769,
      "hv_term_structure": 0.521376
    },
    "3NGL.L": {
      "price": 1.4295,
      "change_pct": -99.999982,
      "vps": 40.90936,
      "mwca": false,
      "vol_regime_pct": 56.972112,
      "hv_term_structure": 0.453834
    },
    "KOLD": {
      "price": 21.9,
      "change_pct": -88.106423,
      "vps": 13.802142,
      "mwca": false,
      "vol_regime_pct": 59.760956,
      "hv_term_structure": 0.535573
    },
    "HND.TO": {
      "price": 4.34,
      "change_pct": -91.418685,
      "vps": 21.518472,
      "mwca": false,
      "vol_regime_pct": 66.135458,
      "hv_term_structure": 0.573826
    },
    "3NGS.L": {
      "price": 12.81,
      "change_pct": -85.849213,
      "vps": 15.719972,
      "mwca": false,
      "vol_regime_pct": 61.354582,
      "hv_term_structure": 0.449985
    }
  }
}