{
  "last_updated": "2026-04-07T19:45:28.685277+00:00",
  "market_status": "open",
  "signals": [
    {
      "type": "vcvi_critical",
      "side": "long",
      "message": "VCVI (126d) = 78.0 \u2014 potential gas bottom \u2014 long/leveraged setup",
      "timestamp": "2026-04-07T19:45:24.715236+00:00",
      "ticker": "BOIL"
    },
    {
      "type": "vcvi_critical",
      "side": "long",
      "message": "VCVI (252d) = 98.3 \u2014 potential gas bottom \u2014 long/leveraged setup",
      "timestamp": "2026-04-07T19:45:24.715236+00:00",
      "ticker": "BOIL"
    },
    {
      "type": "cvi_warning",
      "side": "long",
      "message": "CVI (126d) = 65.6 \u2014 potential gas bottom \u2014 long/leveraged setup",
      "timestamp": "2026-04-07T19:45:24.715236+00:00",
      "ticker": "BOIL"
    },
    {
      "type": "cvi_critical",
      "side": "long",
      "message": "CVI (252d) = 82.7 \u2014 potential gas bottom \u2014 long/leveraged setup",
      "timestamp": "2026-04-07T19:45:24.715236+00:00",
      "ticker": "BOIL"
    },
    {
      "type": "vcvi_critical",
      "side": "long",
      "message": "VCVI (21d) = 73.6 \u2014 potential gas bottom \u2014 long/leveraged setup",
      "timestamp": "2026-04-07T19:45:25.538323+00:00",
      "ticker": "HNU.TO"
    },
    {
      "type": "vcvi_critical",
      "side": "long",
      "message": "VCVI (63d) = 79.7 \u2014 potential gas bottom \u2014 long/leveraged setup",
      "timestamp": "2026-04-07T19:45:25.538323+00:00",
      "ticker": "HNU.TO"
    },
    {
      "type": "vcvi_critical",
      "side": "long",
      "message": "VCVI (126d) = 98.5 \u2014 potential gas bottom \u2014 long/leveraged setup",
      "timestamp": "2026-04-07T19:45:25.538323+00:00",
      "ticker": "HNU.TO"
    },
    {
      "type": "vcvi_critical",
      "side": "long",
      "message": "VCVI (252d) = 111.0 \u2014 potential gas bottom \u2014 long/leveraged setup",
      "timestamp": "2026-04-07T19:45:25.538323+00:00",
      "ticker": "HNU.TO"
    },
    {
      "type": "cvi_warning",
      "side": "long",
      "message": "CVI (63d) = 64.5 \u2014 potential gas bottom \u2014 long/leveraged setup",
      "timestamp": "2026-04-07T19:45:25.538323+00:00",
      "ticker": "HNU.TO"
    },
    {
      "type": "cvi_warning",
      "side": "long",
      "message": "CVI (126d) = 79.6 \u2014 potential gas bottom \u2014 long/leveraged setup",
      "timestamp": "2026-04-07T19:45:25.538323+00:00",
      "ticker": "HNU.TO"
    },
    {
      "type": "cvi_critical",
      "side": "long",
      "message": "CVI (252d) = 89.8 \u2014 potential gas bottom \u2014 long/leveraged setup",
      "timestamp": "2026-04-07T19:45:25.538323+00:00",
      "ticker": "HNU.TO"
    },
    {
      "type": "vcvi_critical",
      "side": "long",
      "message": "VCVI (10d) = 72.7 \u2014 potential gas bottom \u2014 long/leveraged setup",
      "timestamp": "2026-04-07T19:45:26.228018+00:00",
      "ticker": "3NGL.L"
    },
    {
      "type": "vcvi_critical",
      "side": "long",
      "message": "VCVI (21d) = 86.5 \u2014 potential gas bottom \u2014 long/leveraged setup",
      "timestamp": "2026-04-07T19:45:26.228018+00:00",
      "ticker": "3NGL.L"
    },
    {
      "type": "vcvi_critical",
      "side": "long",
      "message": "VCVI (63d) = 86.2 \u2014 potential gas bottom \u2014 long/leveraged setup",
      "timestamp": "2026-04-07T19:45:26.228018+00:00",
      "ticker": "3NGL.L"
    },
    {
      "type": "vcvi_critical",
      "side": "long",
      "message": "VCVI (126d) = 102.1 \u2014 potential gas bottom \u2014 long/leveraged setup",
      "timestamp": "2026-04-07T19:45:26.228018+00:00",
      "ticker": "3NGL.L"
    },
    {
      "type": "vcvi_critical",
      "side": "long",
      "message": "VCVI (252d) = 111.1 \u2014 potential gas bottom \u2014 long/leveraged setup",
      "timestamp": "2026-04-07T19:45:26.228018+00:00",
      "ticker": "3NGL.L"
    },
    {
      "type": "cvi_warning",
      "side": "long",
      "message": "CVI (10d) = 60.5 \u2014 potential gas bottom \u2014 long/leveraged setup",
      "timestamp": "2026-04-07T19:45:26.228018+00:00",
      "ticker": "3NGL.L"
    },
    {
      "type": "cvi_warning",
      "side": "long",
      "message": "CVI (21d) = 72.0 \u2014 potential gas bottom \u2014 long/leveraged setup",
      "timestamp": "2026-04-07T19:45:26.228018+00:00",
      "ticker": "3NGL.L"
    },
    {
      "type": "cvi_warning",
      "side": "long",
      "message": "CVI (63d) = 71.8 \u2014 potential gas bottom \u2014 long/leveraged setup",
      "timestamp": "2026-04-07T19:45:26.228018+00:00",
      "ticker": "3NGL.L"
    },
    {
      "type": "cvi_critical",
      "side": "long",
      "message": "CVI (126d) = 85.0 \u2014 potential gas bottom \u2014 long/leveraged setup",
      "timestamp": "2026-04-07T19:45:26.228018+00:00",
      "ticker": "3NGL.L"
    },
    {
      "type": "cvi_critical",
      "side": "long",
      "message": "CVI (252d) = 92.5 \u2014 potential gas bottom \u2014 long/leveraged setup",
      "timestamp": "2026-04-07T19:45:26.228018+00:00",
      "ticker": "3NGL.L"
    },
    {
      "type": "vcvi_critical",
      "side": "short",
      "message": "VCVI (5d) = 92.5 \u2014 potential gas top \u2014 short/inverse setup",
      "timestamp": "2026-04-07T19:45:27.724724+00:00",
      "ticker": "HND.TO"
    },
    {
      "type": "vcvi_warning",
      "side": "short",
      "message": "VCVI (126d) = 66.6 \u2014 potential gas top \u2014 short/inverse setup",
      "timestamp": "2026-04-07T19:45:27.724724+00:00",
      "ticker": "HND.TO"
    },
    {
      "type": "vcvi_critical",
      "side": "short",
      "message": "VCVI (252d) = 90.5 \u2014 potential gas top \u2014 short/inverse setup",
      "timestamp": "2026-04-07T19:45:27.724724+00:00",
      "ticker": "HND.TO"
    },
    {
      "type": "cvi_warning",
      "side": "short",
      "message": "CVI (5d) = 75.0 \u2014 potential gas top \u2014 short/inverse setup",
      "timestamp": "2026-04-07T19:45:27.724724+00:00",
      "ticker": "HND.TO"
    },
    {
      "type": "cvi_warning",
      "side": "short",
      "message": "CVI (252d) = 73.4 \u2014 potential gas top \u2014 short/inverse setup",
      "timestamp": "2026-04-07T19:45:27.724724+00:00",
      "ticker": "HND.TO"
    }
  ],
  "pair_status": {
    "BOIL_KOLD": "quiet",
    "HNU.TO_HND.TO": "quiet",
    "3NGL.L_3NGS.L": "quiet"
  },
  "etf_summary": {
    "BOIL": {
      "price": 15.715,
      "change_pct": -99.999592,
      "vps": 38.436699,
      "mwca": false,
      "vol_regime_pct": 31.075697,
      "hv_term_structure": 0.390682
    },
    "HNU.TO": {
      "price": 11.66,
      "change_pct": -99.999998,
      "vps": 50.997279,
      "mwca": false,
      "vol_regime_pct": 26.294821,
      "hv_term_structure": 0.396599
    },
    "3NGL.L": {
      "price": 1.3633,
      "change_pct": -99.999983,
      "vps": 53.36151,
      "mwca": false,
      "vol_regime_pct": 29.880478,
      "hv_term_structure": 0.469647
    },
    "KOLD": {
      "price": 22.17,
      "change_pct": -87.95979,
      "vps": 22.963041,
      "mwca": false,
      "vol_regime_pct": 25.498008,
      "hv_term_structure": 0.420341
    },
    "HND.TO": {
      "price": 4.38,
      "change_pct": -91.339595,
      "vps": 56.742128,
      "mwca": false,
      "vol_regime_pct": 26.693227,
      "hv_term_structure": 0.45638
    },
    "3NGS.L": {
      "price": 13.415,
      "change_pct": -85.180889,
      "vps": 23.92441,
      "mwca": false,
      "vol_regime_pct": 34.262948,
      "hv_term_structure": 0.465592
    }
  }
}