{
  "last_updated": "2026-03-24T19:43:52.200249+00:00",
  "market_status": "open",
  "signals": [
    {
      "type": "vcvi_warning",
      "side": "long",
      "message": "VCVI (252d) = 66.5 \u2014 potential gas bottom \u2014 long/leveraged setup",
      "timestamp": "2026-03-24T19:43:49.281617+00:00",
      "ticker": "BOIL"
    },
    {
      "type": "cvi_warning",
      "side": "long",
      "message": "CVI (252d) = 64.0 \u2014 potential gas bottom \u2014 long/leveraged setup",
      "timestamp": "2026-03-24T19:43:49.281617+00:00",
      "ticker": "BOIL"
    },
    {
      "type": "vcvi_warning",
      "side": "long",
      "message": "VCVI (126d) = 69.7 \u2014 potential gas bottom \u2014 long/leveraged setup",
      "timestamp": "2026-03-24T19:43:49.880053+00:00",
      "ticker": "HNU.TO"
    },
    {
      "type": "vcvi_critical",
      "side": "long",
      "message": "VCVI (252d) = 84.6 \u2014 potential gas bottom \u2014 long/leveraged setup",
      "timestamp": "2026-03-24T19:43:49.880053+00:00",
      "ticker": "HNU.TO"
    },
    {
      "type": "cvi_warning",
      "side": "long",
      "message": "CVI (126d) = 69.9 \u2014 potential gas bottom \u2014 long/leveraged setup",
      "timestamp": "2026-03-24T19:43:49.880053+00:00",
      "ticker": "HNU.TO"
    },
    {
      "type": "cvi_critical",
      "side": "long",
      "message": "CVI (252d) = 84.7 \u2014 potential gas bottom \u2014 long/leveraged setup",
      "timestamp": "2026-03-24T19:43:49.880053+00:00",
      "ticker": "HNU.TO"
    },
    {
      "type": "vcvi_warning",
      "side": "long",
      "message": "VCVI (126d) = 70.3 \u2014 potential gas bottom \u2014 long/leveraged setup",
      "timestamp": "2026-03-24T19:43:50.382092+00:00",
      "ticker": "3NGL.L"
    },
    {
      "type": "vcvi_critical",
      "side": "long",
      "message": "VCVI (252d) = 82.3 \u2014 potential gas bottom \u2014 long/leveraged setup",
      "timestamp": "2026-03-24T19:43:50.382092+00:00",
      "ticker": "3NGL.L"
    },
    {
      "type": "cvi_warning",
      "side": "long",
      "message": "CVI (126d) = 74.6 \u2014 potential gas bottom \u2014 long/leveraged setup",
      "timestamp": "2026-03-24T19:43:50.382092+00:00",
      "ticker": "3NGL.L"
    },
    {
      "type": "cvi_critical",
      "side": "long",
      "message": "CVI (252d) = 87.3 \u2014 potential gas bottom \u2014 long/leveraged setup",
      "timestamp": "2026-03-24T19:43:50.382092+00:00",
      "ticker": "3NGL.L"
    }
  ],
  "pair_status": {
    "BOIL_KOLD": "quiet",
    "HNU.TO_HND.TO": "quiet",
    "3NGL.L_3NGS.L": "quiet"
  },
  "etf_summary": {
    "BOIL": {
      "price": 16.25,
      "change_pct": -99.999578,
      "vps": 16.773386,
      "mwca": false,
      "vol_regime_pct": 46.215139,
      "hv_term_structure": 0.513421
    },
    "HNU.TO": {
      "price": 12.08,
      "change_pct": -99.999998,
      "vps": 35.92546,
      "mwca": false,
      "vol_regime_pct": 50.199203,
      "hv_term_structure": 0.521124
    },
    "3NGL.L": {
      "price": 1.454,
      "change_pct": -99.999982,
      "vps": 30.74422,
      "mwca": false,
      "vol_regime_pct": 55.776892,
      "hv_term_structure": 0.476292
    },
    "KOLD": {
      "price": 21.78,
      "change_pct": -88.171593,
      "vps": 28.445665,
      "mwca": false,
      "vol_regime_pct": 49.003984,
      "hv_term_structure": 0.551043
    },
    "HND.TO": {
      "price": 4.31,
      "change_pct": -91.478003,
      "vps": 13.997875,
      "mwca": false,
      "vol_regime_pct": 49.800797,
      "hv_term_structure": 0.592933
    },
    "3NGS.L": {
      "price": 12.92,
      "change_pct": -85.7277,
      "vps": 23.357781,
      "mwca": false,
      "vol_regime_pct": 68.12749,
      "hv_term_structure": 0.511833
    }
  }
}